[
  {
    "id": "1821547",
    "positionType": "PRODUCT",
    "size": 1,
    "price": 392.22,
    "value": 398.573964,
    "plBase": {
      "EUR": -417.25
    },
    "todayPlBase": {
      "EUR": -398.573964
    },
    "breakEvenPrice": 405.33,
    "averageFxRate": 1.0269476,
    "realizedProductPl": -0.997329292,
    "productData": {
      "id": "1821547",
      "name": "ASML Holding NV",
      "isin": "USN070592100",
      "symbol": "ASML",
      "contractSize": 1,
      "productType": "STOCK",
      "productTypeId": 1,
      "tradable": true,
      "category": "B",
      "currency": "USD",
      "active": true,
      "exchangeId": "663",
      "onlyEodPrices": false,
      "orderTimeTypes": ["DAY", "GTC"],
      "buyOrderTypes": ["LIMIT", "MARKET", "STOPLOSS", "STOPLIMIT"],
      "sellOrderTypes": ["LIMIT", "MARKET", "STOPLOSS", "STOPLIMIT"],
      "productBitTypes": [],
      "closePrice": 392.22,
      "closePriceDate": "2022-10-17",
      "feedQuality": "BT",
      "orderBookDepth": 0,
      "vwdIdentifierType": "vwdkey",
      "vwdId": "ASML.BATS,E",
      "qualitySwitchable": false,
      "qualitySwitchFree": false,
      "vwdModuleId": 31,
      "feedQualitySecondary": "D15",
      "orderBookDepthSecondary": 0,
      "vwdIdentifierTypeSecondary": "issueid",
      "vwdIdSecondary": "350016923",
      "qualitySwitchableSecondary": true,
      "qualitySwitchFreeSecondary": false,
      "vwdModuleIdSecondary": 21
    }
  },
  {
    "id": "14625503",
    "positionType": "PRODUCT",
    "size": 5,
    "price": 42.54,
    "value": 212.7,
    "plBase": {
      "EUR": -215.1
    },
    "todayPlBase": {
      "EUR": -212.7
    },
    "breakEvenPrice": 42.42,
    "averageFxRate": 1,
    "realizedProductPl": -3,
    "productData": {
      "id": "14625503",
      "name": "BE Semiconductor Industries NV",
      "isin": "NL0012866412",
      "symbol": "BESI",
      "contractSize": 1,
      "productType": "STOCK",
      "productTypeId": 1,
      "tradable": true,
      "category": "C",
      "currency": "EUR",
      "active": true,
      "exchangeId": "200",
      "onlyEodPrices": false,
      "orderTimeTypes": ["DAY", "GTC"],
      "buyOrderTypes": ["LIMIT", "MARKET", "STOPLOSS", "STOPLIMIT"],
      "sellOrderTypes": ["LIMIT", "MARKET", "STOPLOSS", "STOPLIMIT"],
      "productBitTypes": [],
      "closePrice": 42.54,
      "closePriceDate": "2022-10-17",
      "feedQuality": "R",
      "orderBookDepth": 0,
      "vwdIdentifierType": "issueid",
      "vwdId": "11820",
      "qualitySwitchable": false,
      "qualitySwitchFree": false,
      "vwdModuleId": 1
    }
  },
  {
    "id": "1153605",
    "positionType": "PRODUCT",
    "size": 2,
    "price": 219.35,
    "value": 445.80694,
    "plBase": {
      "EUR": -474.01
    },
    "todayPlBase": {
      "EUR": -445.80694
    },
    "breakEvenPrice": 230.25,
    "averageFxRate": 1.0250006262757871,
    "realizedProductPl": -1.9972116,
    "productData": {
      "id": "1153605",
      "name": "Tesla",
      "isin": "US88160R1014",
      "symbol": "TSLA",
      "contractSize": 1,
      "productType": "STOCK",
      "productTypeId": 1,
      "tradable": true,
      "category": "C",
      "currency": "USD",
      "active": true,
      "exchangeId": "663",
      "onlyEodPrices": false,
      "orderTimeTypes": ["DAY", "GTC"],
      "buyOrderTypes": ["LIMIT", "MARKET", "STOPLOSS", "STOPLIMIT"],
      "sellOrderTypes": ["LIMIT", "MARKET", "STOPLOSS", "STOPLIMIT"],
      "productBitTypes": ["US_RAS_GREEN_LIST"],
      "closePrice": 219.35,
      "closePriceDate": "2022-10-17",
      "feedQuality": "BT",
      "orderBookDepth": 0,
      "vwdIdentifierType": "vwdkey",
      "vwdId": "TSLA.BATS,E",
      "qualitySwitchable": false,
      "qualitySwitchFree": false,
      "vwdModuleId": 31,
      "feedQualitySecondary": "D15",
      "orderBookDepthSecondary": 0,
      "vwdIdentifierTypeSecondary": "issueid",
      "vwdIdSecondary": "350000520",
      "qualitySwitchableSecondary": true,
      "qualitySwitchFreeSecondary": false,
      "vwdModuleIdSecondary": 21
    }
  },
  {
    "id": "4879564",
    "positionType": "PRODUCT",
    "size": 10,
    "price": 13.2,
    "value": 134.1384,
    "plBase": {
      "EUR": -135.52
    },
    "todayPlBase": {
      "EUR": -134.1384
    },
    "breakEvenPrice": 13.13,
    "averageFxRate": 1.0245337,
    "realizedProductPl": -0.99872519,
    "productData": {
      "id": "4879564",
      "name": "American Airlines Group Inc",
      "isin": "US02376R1023",
      "symbol": "AAL",
      "contractSize": 1,
      "productType": "STOCK",
      "productTypeId": 1,
      "tradable": true,
      "category": "C",
      "currency": "USD",
      "active": true,
      "exchangeId": "663",
      "onlyEodPrices": false,
      "orderTimeTypes": ["DAY", "GTC"],
      "buyOrderTypes": ["LIMIT", "MARKET", "STOPLOSS", "STOPLIMIT"],
      "sellOrderTypes": ["LIMIT", "MARKET", "STOPLOSS", "STOPLIMIT"],
      "productBitTypes": ["US_RAS_GREEN_LIST"],
      "closePrice": 13.2,
      "closePriceDate": "2022-10-17",
      "feedQuality": "BT",
      "orderBookDepth": 0,
      "vwdIdentifierType": "vwdkey",
      "vwdId": "AAL.BATS,E",
      "qualitySwitchable": false,
      "qualitySwitchFree": false,
      "vwdModuleId": 31,
      "feedQualitySecondary": "D15",
      "orderBookDepthSecondary": 0,
      "vwdIdentifierTypeSecondary": "issueid",
      "vwdIdSecondary": "350009083",
      "qualitySwitchableSecondary": true,
      "qualitySwitchFreeSecondary": false,
      "vwdModuleIdSecondary": 21
    }
  }
]
